Workbook

Sheet Summary
A1: Summary - What it costs to ship SuCAR
A3: Metric | B3: Lean (MVP) | C3: Standard (Prod) | D3: Notes
A4: One-time (hard cash to launch) | B4: ='Cost Breakdown'!$K$4+'Cost Breakdown'!$K$6 | C4: ='Cost Breakdown'!$K$5+'Cost Breakdown'!$K$7 | D4: Apple $99 + Play $25 + domain $15 - covers ALL apps & web surfaces
A5: Monthly run-rate | B5: ='Cost Breakdown'!$K$8 | C5: ='Cost Breakdown'!$K$9+Assumptions!$B$8 | D5: All recurring services; Twilio OFF by default (email+Google sign-in)
A6: Year-1 total (fixed) | B6: ='12-Month Projection'!N6 | C6: ='12-Month Projection'!N11 | D6: Recurring x 12 + one-time + annual
A7: Year-1 total in Kwacha | B7: =B6*Assumptions!$B$5 | C7: =C6*Assumptions!$B$5 | D7: At the FX rate on Assumptions
A9: Maps + navigation + tracking | B9: 0 | C9: 0 | D9: Mapbox free tier + Supabase realtime + deep-link nav -> $0 at pilot scale
A10: Optional one-time build/labor | B10: ='Surfaces & Deliverables'!$E$11 | C10: ='Surfaces & Deliverables'!$E$11 | D10: From Surfaces tab; 0 if in-house / AI-built
A11: Variable: payment fees / yr | B11: ='Cost Breakdown'!$H$24 | C11: ='Cost Breakdown'!$H$24 | D11: Revenue-linked (~2% of digital GMV); $0 if cash-only
A13: Read me
A14: - Landing + Admin + Operator dashboards are ONE web app - one hosting + domain bill covers all three.
A15: - Client + Driver apps are ONE Expo codebase; one Apple + one Google account covers all 4 store listings.
A16: - Maps/navigation/tracking cost $0 at pilot: Mapbox free tier, Supabase realtime, and deep-link to Google Maps/Waze for driving.
A17: - Twilio is NOT free. Default plan ships with email + Google sign-in only (Twilio $0). Set 'Phone OTP enabled?'=1 on Assumptions to add it.
A18: - A car wash is a physical service, so Apple/Google take 0% commission - use normal payment rails.
A19: - Change blue inputs on Assumptions (FX, GMV, fee %, EAS, Phone OTP) - every total recalculates.

Sheet Assumptions
A1: SuCAR - Deployment Budget · Assumptions & Inputs
A2: Blue cells are inputs you can change. Everything else recalculates.
A4: Assumption | B4: Value | C4: Unit | D4: Note
A5: FX rate (ZMW per USD) | B5: 27 | C5: K/$ | D5: Approximate - verify the live rate
A6: Digital-payment GMV (monthly) | B6: 0 | C6: USD | D6: 0 = cash-only v1; set if processing mobile money/cards
A7: Payment processing fee | B7: 0.02 | C7: % | D7: Zambian aggregator ~1.5%-3% per transaction
A8: EAS Production add-on (optional) | B8: 0 | C8: USD/mo | D8: Set to 99 only if you need fast concurrent mobile builds
A9: Phone OTP enabled? (1=yes, 0=no) | B9: 0 | C9: flag | D9: Email + Google sign-in are FREE. Phone OTP (Twilio) is NOT - default OFF for v1.

Sheet Cost Breakdown
A1: Cost Breakdown - Lean (MVP) vs Standard (Production)
A3: Item | B3: Phase | C3: Type | D3: Factor (/yr) | E3: Lean unit ($) | F3: Standard unit ($) | G3: Lean Yr-1 ($) | H3: Standard Yr-1 ($) | J3: Helper (by type)
A4: Google Play Developer account (covers BOTH apps) | B4: 5 | C4: One-time | D4: =IF(C4="Monthly",12,1) | E4: 25 | F4: 25 | G4: =E4*D4 | H4: =F4*D4 | J4: One-time Lean | K4: =SUMIFS($E$4:$E$20,$C$4:$C$20,"One-time")
A5: Apple Developer Program (covers BOTH apps) | B5: 5 | C5: Annual | D5: =IF(C5="Monthly",12,1) | E5: 99 | F5: 99 | G5: =E5*D5 | H5: =F5*D5 | J5: One-time Std | K5: =SUMIFS($F$4:$F$20,$C$4:$C$20,"One-time")
A6: Domain name (.com + subdomains app./admin.) | B6: 4 | C6: Annual | D6: =IF(C6="Monthly",12,1) | E6: 15 | F6: 15 | G6: =E6*D6 | H6: =F6*D6 | J6: Annual Lean | K6: =SUMIFS($E$4:$E$20,$C$4:$C$20,"Annual")
A7: Privacy / Terms legal review (optional) | B7: 7 | C7: One-time | D7: =IF(C7="Monthly",12,1) | E7: 0 | F7: 0 | G7: =E7*D7 | H7: =F7*D7 | J7: Annual Std | K7: =SUMIFS($F$4:$F$20,$C$4:$C$20,"Annual")
A8: Supabase (database + auth + REALTIME tracking) | B8: 3 | C8: Monthly | D8: =IF(C8="Monthly",12,1) | E8: 0 | F8: 25 | G8: =E8*D8 | H8: =F8*D8 | J8: Monthly Lean | K8: =SUMIFS($E$4:$E$20,$C$4:$C$20,"Monthly")
A9: Web hosting (landing + admin + operator + API) | B9: 4 | C9: Monthly | D9: =IF(C9="Monthly",12,1) | E9: 7 | F9: 25 | G9: =E9*D9 | H9: =F9*D9 | J9: Monthly Std | K9: =SUMIFS($F$4:$F$20,$C$4:$C$20,"Monthly")
A10: SSL certificate (Let's Encrypt / host) | B10: 4 | C10: Monthly | D10: =IF(C10="Monthly",12,1) | E10: 0 | F10: 0 | G10: =E10*D10 | H10: =F10*D10
A11: Internet / business data (team) | B11: 8 | C11: Monthly | D11: =IF(C11="Monthly",12,1) | E11: 20 | F11: 50 | G11: =E11*D11 | H11: =F11*D11
A12: Transactional email (Resend / SendGrid) | B12: 8 | C12: Monthly | D12: =IF(C12="Monthly",12,1) | E12: 0 | F12: 20 | G12: =E12*D12 | H12: =F12*D12
A13: Business email (Google Workspace, support@) | B13: 8 | C13: Monthly | D13: =IF(C13="Monthly",12,1) | E13: 0 | F13: 6 | G13: =E13*D13 | H13: =F13*D13
A14: Error monitoring (Sentry) | B14: 4 | C14: Monthly | D14: =IF(C14="Monthly",12,1) | E14: 0 | F14: 26 | G14: =E14*D14 | H14: =F14*D14
A15: EAS Build (mobile CI, both apps) | B15: 5 | C15: Monthly | D15: =IF(C15="Monthly",12,1) | E15: 0 | F15: 0 | G15: =E15*D15 | H15: =F15*D15
A16: Mapbox - maps + geocoding + directions | B16: 5 | C16: Monthly | D16: =IF(C16="Monthly",12,1) | E16: 0 | F16: 0 | G16: =E16*D16 | H16: =F16*D16
A17: Real-time driver tracking (via Supabase) | B17: 5 | C17: Monthly | D17: =IF(C17="Monthly",12,1) | E17: 0 | F17: 0 | G17: =E17*D17 | H17: =F17*D17
A18: Push notifications (Expo) | B18: 5 | C18: Monthly | D18: =IF(C18="Monthly",12,1) | E18: 0 | F18: 0 | G18: =E18*D18 | H18: =F18*D18
A19: Twilio (phone OTP) - OFF by default | B19: 8 | C19: Monthly | D19: =IF(C19="Monthly",12,1) | E19: 0 | F19: =55*Assumptions!$B$9 | G19: =E19*D19 | H19: =F19*D19
A20: Google OAuth + email sign-in | B20: 5 | C20: One-time | D20: =IF(C20="Monthly",12,1) | E20: 0 | F20: 0 | G20: =E20*D20 | H20: =F20*D20
A21: TOTAL (Year 1, fixed) | G21: =SUM(G4:G20) | H21: =SUM(H4:H20)
A23: Variable: payment processing (revenue-linked)
A24: Estimated annual payment fees | B24: =GMV x 12 x fee% (0 if cash-only) | H24: =Assumptions!$B$6*12*Assumptions!$B$7

Sheet Tech & Cost Decisions
A1: Tech & Cost Decisions (specialist recommendations)
A3: Area | B3: Recommendation | C3: Cost impact
A4: Maps provider | B4: Stay on MAPBOX for v1 - already integrated, free tier covers the pilot, and you don't depend on its POI data (your car washes are your own DB records). | C4: $0 (free tier)
A5: Google Maps? | B5: Only switch/hybrid later if you need premium traffic ETAs or richer address autocomplete. Generally pricier than Mapbox above free tier. | C5: Defer
A6: Driver navigation | B6: Deep-link to the driver's Google Maps / Waze app for the actual drive instead of building in-app turn-by-turn. Free, traffic-aware, best-in-class. | C6: $0
A7: Real-time tracking | B7: Driver location -> Supabase realtime websocket -> client; the map only renders the moving marker. NOT a maps-vendor charge. | C7: Included in Supabase
A8: Mobile map tech | B8: When time allows, move the WebView map to the native @rnmapbox/maps SDK for smoother tracking (still Mapbox, still free). | C8: $0
A9: Phone OTP | B9: Launch with EMAIL + GOOGLE sign-in only (both free). Defer phone OTP - Twilio is not free (~$55/mo at ~1k verifications). | C9: $0 (vs ~$55/mo)
A10: Phone OTP later | B10: If/when needed, compare Firebase Phone Auth (free monthly allowance) and a local Zambian SMS aggregator vs Twilio. | C10: Variable

Sheet Surfaces & Deliverables
A1: Surfaces & Deliverables - what each one costs to run
A2: All product surfaces share the infrastructure already budgeted - no per-surface hosting or store fees.
A4: Surface | B4: Platform | C4: Covered by (already budgeted) | D4: Extra infra cost | E4: Build effort (optional, $)
A5: Landing page | B5: Web | C5: Web hosting + domain | D5: 0 | E5: 0
A6: Admin panel | B6: Web | C6: Same web app / deploy | D6: 0 | E6: 0
A7: Operator (car wash) dashboard | B7: Web | C7: Same web app / deploy | D7: 0 | E7: 0
A8: Backend API | B8: Server | C8: Web hosting + Supabase | D8: 0 | E8: 0
A9: Client app | B9: iOS + Android | C9: One Expo codebase + EAS + store accounts | D9: 0 | E9: 0
A10: Driver app | B10: iOS + Android | C10: Same Expo codebase (variant) + store accounts | D10: 0 | E10: 0
A11: TOTAL | D11: =SUM(D5:D10) | E11: =SUM(E5:E10)
A13: Note: 'Build effort' is optional one-time labor if you contract help. Leave 0 if building in-house / with AI.

Sheet 12-Month Projection
A1: 12-Month Cash Projection (USD)
A3: Line | B3: M1 | C3: M2 | D3: M3 | E3: M4 | F3: M5 | G3: M6 | H3: M7 | I3: M8 | J3: M9 | K3: M10 | L3: M11 | M3: M12 | N3: Year 1
A4: Lean - recurring | B4: ='Cost Breakdown'!$K$8 | C4: ='Cost Breakdown'!$K$8 | D4: ='Cost Breakdown'!$K$8 | E4: ='Cost Breakdown'!$K$8 | F4: ='Cost Breakdown'!$K$8 | G4: ='Cost Breakdown'!$K$8 | H4: ='Cost Breakdown'!$K$8 | I4: ='Cost Breakdown'!$K$8 | ... M4: ='Cost Breakdown'!$K$8 | N4: =SUM(B4:M4)
A5: Lean - one-time & annual | B5: ='Cost Breakdown'!$K$4+'Cost Breakdown'!$K$6 | C5: 0 | D5: 0 | E5: 0 | F5: 0 | G5: 0 | H5: 0 | I5: 0 | J5: 0 | K5: 0 | L5: 0 | M5: 0 | N5: =SUM(B5:M5)
A6: Lean - total monthly | B6: =B4+B5 | C6: =C4+C5 | D6: =D4+D5 | E6: =E4+E5 | F6: =F4+F5 | G6: =G4+G5 | H6: =H4+H5 | I6: =I4+I5 | ... M6: =M4+M5 | N6: =SUM(B6:M6)
A7: Lean - cumulative | B7: =B6 | C7: =B7+C6 | D7: =C7+D6 | E7: =D7+E6 | F7: =E7+F6 | G7: =F7+G6 | H7: =G7+H6 | I7: =H7+I6 | J7: =I7+J6 | ... M7: =L7+M6 | N7: =N6
A9: Standard - recurring | B9: ='Cost Breakdown'!$K$9 | C9: ='Cost Breakdown'!$K$9 | D9: ='Cost Breakdown'!$K$9 | E9: ='Cost Breakdown'!$K$9 | F9: ='Cost Breakdown'!$K$9 | G9: ='Cost Breakdown'!$K$9 | H9: ='Cost Breakdown'!$K$9 | I9: ='Cost Breakdown'!$K$9 | ... M9: ='Cost Breakdown'!$K$9 | N9: =SUM(B9:M9)
A10: Standard - one-time & annual | B10: ='Cost Breakdown'!$K$5+'Cost Breakdown'!$K$7 | C10: 0 | D10: 0 | E10: 0 | F10: 0 | G10: 0 | H10: 0 | I10: 0 | J10: 0 | K10: 0 | L10: 0 | M10: 0 | N10: =SUM(B10:M10)
A11: Standard - total monthly | B11: =B9+B10 | C11: =C9+C10 | D11: =D9+D10 | E11: =E9+E10 | F11: =F9+F10 | G11: =G9+G10 | H11: =H9+H10 | I11: =I9+I10 | ... M11: =M9+M10 | N11: =SUM(B11:M11)
A12: Standard - cumulative | B12: =B11 | C12: =B12+C11 | D12: =C12+D11 | E12: =D12+E11 | F12: =E12+F11 | G12: =F12+G11 | H12: =G12+H11 | I12: =H12+I11 | J12: =I12+J11 | ... M12: =L12+M11 | N12: =N11
